pcdkit/__init__.py
pcdkit/factory.py
pcdkit/in_memory.py
pcdkit/memmap.py
pcdkit/pcd_loader.py
pcdkit/pcd_metadata.py
pcdkit/point_cloud.py
pcdkit/typings.py
pcdkit/utils.py
pcdkit-0.2.14.dist-info/licenses/LICENSES.txt
pcdkit-0.2.14.dist-info/METADATA
pcdkit-0.2.14.dist-info/WHEEL
pcdkit-0.2.14.dist-info/top_level.txt
pcdkit-0.2.14.dist-info/RECORD
