Metadata-Version: 2.4
Name: pcdkit
Version: 0.2.14
Summary: A lightweight PCD file processing library
Author-email: Fledge Shiu <xzk0701@gmail.com>
License-Expression: MIT
Project-URL: Homepage, https://github.com/FledgeXu/PCDKit
Project-URL: Repository, https://github.com/FledgeXu/PCDKit
Requires-Python: >=3.7
License-File: LICENSES.txt
Requires-Dist: numpy
Requires-Dist: python-neo-lzf
Requires-Dist: numba
Requires-Dist: typing-extensions
Dynamic: license-file
